swmm_utils/__init__.py
swmm_utils/inp.py
swmm_utils/inp_decoder.py
swmm_utils/inp_encoder.py
swmm_utils/out.py
swmm_utils/out_decoder.py
swmm_utils/out_encoder.py
swmm_utils/rpt.py
swmm_utils/rpt_decoder.py
swmm_utils-0.5.0.dist-info/licenses/LICENSE
swmm_utils-0.5.0.dist-info/METADATA
swmm_utils-0.5.0.dist-info/WHEEL
swmm_utils-0.5.0.dist-info/top_level.txt
swmm_utils-0.5.0.dist-info/RECORD
